{"title":"Food.Glorious.Food.S01E09.HDTV.x264-BARGE","uid":8653789,"size":391662500,"categoryP":"video","categoryS":"tv_shows","magnet":"?xt=urn:btih:0427211f71c57923217435a17dfad08ee3787973&amp;dn=Food.Glorious.Food.S01E09.HDTV.x264-BARGE&amp;tr=udp%3A%2F%2Ftracker.openbittorrent.com%3A80&amp;tr=udp%3A%2F%2Fopen.demonii.com%3A1337&amp;tr=udp%3A%2F%2Ftracker.coppersurfer.tk%3A6969&amp;tr=udp%3A%2F%2Fexodus.desync.com%3A6969","seeders":1,"leechers":0,"uploader":"TvTeam","files":4,"time":1373167378,"description":"::::::::::::::::::::::::::::::::::::::::::::::::::::::::::::::::::::::::::\n  &lt;a href=&quot;\nhttp://www.torrenting.com&quot; rel=&quot;nofollow&quot; target=&quot;_NEW&quot;&gt;\nhttp://www.torrenting.com&lt;/a&gt;\n\n::::::::::::::::::::::::::::::::::::::::::::::::::::::::::::::::::::::::::\n\n(((((((((((((= Enjoy No RAR releases =))))))))))))))))))))\n\n\nMust Try:  &lt;a href=&quot; http://www.torrenting.com&quot; rel=&quot;nofollow&quot; target=&quot;_NEW&quot;&gt; http://www.torrenting.com&lt;/a&gt;","torrent":{"xt":"urn:btih:0427211f71c57923217435a17dfad08ee3787973","amp;dn":"Food.Glorious.Food.S01E09.HDTV.x264-BARGE","amp;tr":["udp%3A%2F%2Ftracker.openbittorrent.com%3A80","udp%3A%2F%2Fopen.demonii.com%3A1337","udp%3A%2F%2Ftracker.coppersurfer.tk%3A6969","udp%3A%2F%2Fexodus.desync.com%3A6969"],"infoHash":"0427211f71c57923217435a17dfad08ee3787973","infoHashBuffer":{"type":"Buffer","data":[4,39,33,31,113,197,121,35,33,116,53,161,125,250,208,142,227,120,121,115]},"announce":[],"urlList":[]}}