{"title":"Official.Howard.Stern.Show.Parody.XXX.DVDRip.XviD-Jiggly","uid":6479059,"size":1464819967,"categoryP":"porn","categoryS":"movies","magnet":"?xt=urn:btih:057ff8672950cab4f540f9f8fa904a2e114eba35&amp;dn=Official.Howard.Stern.Show.Parody.XXX.DVDRip.XviD-Jiggly&amp;tr=udp%3A%2F%2Ftracker.openbittorrent.com%3A80&amp;tr=udp%3A%2F%2Fopen.demonii.com%3A1337&amp;tr=udp%3A%2F%2Ftracker.coppersurfer.tk%3A6969&amp;tr=udp%3A%2F%2Fexodus.desync.com%3A6969","seeders":1,"leechers":0,"uploader":"exmnova","files":4,"time":1308424663,"description":"Official.Howard.Stern.Show.Parody.XXX.DVDRip.XviD-Jiggly\n\n\n\nStarring:    Kagney Linn Karter, Jada fire, Breanne Benson, Bobbi Starr, Amy Brooke, Jaelyn Fox, Ryan McLane, Mark Wood, Dale Dabone, Will Powers, Anthony Rosano\n\n\n\nScreens / More Info:\n\n\n &lt;a href=&quot;\nhttp://www.69bits.com/torrent/Feature/34178/Official.Howard.Stern.Show.Parody.XXX.DVDRip.XviD-Jiggly.html&quot; rel=&quot;nofollow&quot; target=&quot;_NEW&quot;&gt;\nhttp://www.69bits.com/torrent/Feature/34178/Official.Howard.Stern.Show.Parody.XXX.DVDRip.XviD-Jiggly.html&lt;/a&gt;","torrent":{"xt":"urn:btih:057ff8672950cab4f540f9f8fa904a2e114eba35","amp;dn":"Official.Howard.Stern.Show.Parody.XXX.DVDRip.XviD-Jiggly","amp;tr":["udp%3A%2F%2Ftracker.openbittorrent.com%3A80","udp%3A%2F%2Fopen.demonii.com%3A1337","udp%3A%2F%2Ftracker.coppersurfer.tk%3A6969","udp%3A%2F%2Fexodus.desync.com%3A6969"],"infoHash":"057ff8672950cab4f540f9f8fa904a2e114eba35","infoHashBuffer":{"type":"Buffer","data":[5,127,248,103,41,80,202,180,245,64,249,248,250,144,74,46,17,78,186,53]},"announce":[],"urlList":[]}}