{"title":"Windows XP Crack","uid":5464531,"size":150654,"categoryP":"applications","categoryS":"windows","magnet":"?xt=urn:btih:0a77e18b1ef44445e5e78f095440603e5367fb31&amp;dn=Windows+XP+Crack&amp;tr=udp%3A%2F%2Ftracker.openbittorrent.com%3A80&amp;tr=udp%3A%2F%2Fopen.demonii.com%3A1337&amp;tr=udp%3A%2F%2Ftracker.coppersurfer.tk%3A6969&amp;tr=udp%3A%2F%2Fexodus.desync.com%3A6969","seeders":1,"leechers":0,"uploader":"je2854","files":1,"time":1269572531,"description":"I have worked out where all you have to do\n\nis double click this and it will bring up\n\na 'WGA Fixer' and then install the other DLL\n\n\nNOW HEAR THIS!!\n\nSince this harmless BUT ANTI-Viruses know\n\nthat this shouldn't happen they WILL flag it\n\nas a 'PUP' or 'Generic-Like virus' \n\nBut nonetheless it is in an executable that\n\nwill elevate the hassle on what to do, so\n\nnow even a noob that just installed an OS\n\nwithout a legit key would know what to do.\n\n\nIt has been created with WinRAR Corporate\n\nso if you do not trust me then extract it \n\nand run the individual components themselves ","torrent":{"xt":"urn:btih:0a77e18b1ef44445e5e78f095440603e5367fb31","amp;dn":"Windows+XP+Crack","amp;tr":["udp%3A%2F%2Ftracker.openbittorrent.com%3A80","udp%3A%2F%2Fopen.demonii.com%3A1337","udp%3A%2F%2Ftracker.coppersurfer.tk%3A6969","udp%3A%2F%2Fexodus.desync.com%3A6969"],"infoHash":"0a77e18b1ef44445e5e78f095440603e5367fb31","infoHashBuffer":{"type":"Buffer","data":[10,119,225,139,30,244,68,69,229,231,143,9,84,64,96,62,83,103,251,49]},"announce":[],"urlList":[]}}