{"title":"[MilfHunter] Rachel (Pussy Pearls / 03.03.2014)","uid":9689046,"size":412851975,"categoryP":"porn","categoryS":"movies","magnet":"?xt=urn:btih:18f05fc26eb5de517ee135bfb3d1e71ad028e5d1&amp;dn=%5BMilfHunter%5D+Rachel+%28Pussy+Pearls+%2F+03.03.2014%29&amp;tr=udp%3A%2F%2Ftracker.openbittorrent.com%3A80&amp;tr=udp%3A%2F%2Fopen.demonii.com%3A1337&amp;tr=udp%3A%2F%2Ftracker.coppersurfer.tk%3A6969&amp;tr=udp%3A%2F%2Fexodus.desync.com%3A6969","seeders":1,"leechers":4,"uploader":"chkm8te","files":1,"time":1393830595,"description":"[MilfHunter] Rachel (Pussy Pearls / 03.03.2014)\n\nSo Levi and I where hanging around last week when we got a call from a realtor lady named Rachel that was at the front gate looking to get in. We never posted anything about the property being for sale, but we where curios enough since she sounded hot on the phone. Rachel pulled up looking very sexy, so we showed her around. Turns out she was heading out after to pick up her kid from day care. This MILF was flirting with Levi the entire time, so we brought her in the room and got straight to the point. Levi motivated her to throw in some extra incentives to close the big deal for her boss. After that Rachel warmed up and let Levi have his way with her. Come check out Levi pounding this MILF until she couldn't take anymore.\n\nScreens: &lt;a href=&quot;\nhttp://xxxhost.me/viewer.php?file=ek21ynpoqoks6vh06krv.jpg&quot; rel=&quot;nofollow&quot; target=&quot;_NEW&quot;&gt;\nhttp://xxxhost.me/viewer.php?file=ek21ynpoqoks6vh06krv.jpg&lt;/a&gt;\n &lt;a href=&quot;\nhttp://xxxhost.me/viewer.php?file=qu2ztf1iljvckfq24qjh.jpg&quot; rel=&quot;nofollow&quot; target=&quot;_NEW&quot;&gt;\nhttp://xxxhost.me/viewer.php?file=qu2ztf1iljvckfq24qjh.jpg&lt;/a&gt;","torrent":{"xt":"urn:btih:18f05fc26eb5de517ee135bfb3d1e71ad028e5d1","amp;dn":"%5BMilfHunter%5D+Rachel+%28Pussy+Pearls+%2F+03.03.2014%29","amp;tr":["udp%3A%2F%2Ftracker.openbittorrent.com%3A80","udp%3A%2F%2Fopen.demonii.com%3A1337","udp%3A%2F%2Ftracker.coppersurfer.tk%3A6969","udp%3A%2F%2Fexodus.desync.com%3A6969"],"infoHash":"18f05fc26eb5de517ee135bfb3d1e71ad028e5d1","infoHashBuffer":{"type":"Buffer","data":[24,240,95,194,110,181,222,81,126,225,53,191,179,209,231,26,208,40,229,209]},"announce":[],"urlList":[]}}