{"title":"Scapegoat Wax - Luxurious (Original Release 1999)","uid":7098073,"size":167792640,"categoryP":"audio","categoryS":"music","magnet":"?xt=urn:btih:1966cbcc7209e6079e2c11fa7c05b356264a8a2e&amp;dn=Scapegoat+Wax+-+Luxurious+%28Original+Release+1999%29&amp;tr=udp%3A%2F%2Ftracker.openbittorrent.com%3A80&amp;tr=udp%3A%2F%2Fopen.demonii.com%3A1337&amp;tr=udp%3A%2F%2Ftracker.coppersurfer.tk%3A6969&amp;tr=udp%3A%2F%2Fexodus.desync.com%3A6969","seeders":1,"leechers":0,"uploader":"Sackilla666","files":-1,"time":1331622902,"description":"Scapegoat Wax - Luxurious\nRated Z Records 1999\n\nTracks:\n\n1.  Revenge of the Dope Fiend Beat\n2.  Luxurious\n3.  Aisle 10\n4.  Crawlin'\n5.  Light of the Moon\n6.  Shortkut on the Scratch\n7.  Freeway\n8.  Random Violence\n9.  Eardrum\n10. Evelyn\n11. Space to Share\n12. Numb and Nervous\n13. Sametime\n14. Dead in a Cave\n15. Wishing Well\n16. Strain (Weirdo)\n17. Party of One\n18. Animal Disquise\n19. Almost Fine\n\n2 Reviews from Amazon.com pieced together to sum up the album.\n\nThe Original Edition of the classic album later released on Beastie Boys' Grand Royal imprint. This is the raw pre-Mario Caldato Jr-ized (and better) version of the album that would become SWAX.  From the writer/producer of hits from Baby Bash, Paula Deanda, The Grouch, Luckyiam PSC, The Federation, Mozella, etc!\n\nIf you like the album then go buy it.","torrent":{"xt":"urn:btih:1966cbcc7209e6079e2c11fa7c05b356264a8a2e","amp;dn":"Scapegoat+Wax+-+Luxurious+%28Original+Release+1999%29","amp;tr":["udp%3A%2F%2Ftracker.openbittorrent.com%3A80","udp%3A%2F%2Fopen.demonii.com%3A1337","udp%3A%2F%2Ftracker.coppersurfer.tk%3A6969","udp%3A%2F%2Fexodus.desync.com%3A6969"],"infoHash":"1966cbcc7209e6079e2c11fa7c05b356264a8a2e","infoHashBuffer":{"type":"Buffer","data":[25,102,203,204,114,9,230,7,158,44,17,250,124,5,179,86,38,74,138,46]},"announce":[],"urlList":[]}}