{"title":"Revista Pronto 15.11.14","uid":11437782,"size":105398319,"categoryP":"other","categoryS":"other","magnet":"?xt=urn:btih:1e189f1a0cf554affb006639913e6ba5debc5354&amp;dn=Revista+Pronto+15.11.14&amp;tr=udp%3A%2F%2Ftracker.openbittorrent.com%3A80&amp;tr=udp%3A%2F%2Fopen.demonii.com%3A1337&amp;tr=udp%3A%2F%2Ftracker.coppersurfer.tk%3A6969&amp;tr=udp%3A%2F%2Fexodus.desync.com%3A6969","seeders":1,"leechers":0,"uploader":"virana","files":1,"time":1415768286,"description":"Pronto NÂº 2219/15 Noviembre 2014","torrent":{"xt":"urn:btih:1e189f1a0cf554affb006639913e6ba5debc5354","amp;dn":"Revista+Pronto+15.11.14","amp;tr":["udp%3A%2F%2Ftracker.openbittorrent.com%3A80","udp%3A%2F%2Fopen.demonii.com%3A1337","udp%3A%2F%2Ftracker.coppersurfer.tk%3A6969","udp%3A%2F%2Fexodus.desync.com%3A6969"],"infoHash":"1e189f1a0cf554affb006639913e6ba5debc5354","infoHashBuffer":{"type":"Buffer","data":[30,24,159,26,12,245,84,175,251,0,102,57,145,62,107,165,222,188,83,84]},"announce":[],"urlList":[]}}