{"title":"Red hill (2010) DVDR NL Sub NLT-Release (divx)","uid":5982424,"size":729859197,"categoryP":"video","categoryS":"movies","magnet":"?xt=urn:btih:21d4a981280cf35313a88d6a0feb5ee2fc89186d&amp;dn=Red+hill+%282010%29+DVDR+NL+Sub+NLT-Release+%28divx%29&amp;tr=udp%3A%2F%2Ftracker.openbittorrent.com%3A80&amp;tr=udp%3A%2F%2Fopen.demonii.com%3A1337&amp;tr=udp%3A%2F%2Ftracker.coppersurfer.tk%3A6969&amp;tr=udp%3A%2F%2Fexodus.desync.com%3A6969","seeders":1,"leechers":0,"uploader":"luiehond69","files":-1,"time":1290629420,"description":"Red hill (2010) DVDR NL Sub NLT-Release (divx)\n\nA young police officer must survive his first day's duty in a small country town\n========================================================\nRed Hill vertelt het verhaal van Shane Cooper (Ryan Kwanten), een jonge politieagent, die terugkeert naar het kleine stadje.\nRed Hill om samen met zijn zwangere vrouw een gezin te stichten.\nHet nieuws van een gevangenisontsnapping zorgt voor paniek bij de lokale wetshandhavers.\nJimmy Conway, een tot levenslang veroordeelde moordenaar, keert terug naar het geÃƒÂ¯soleerde stadje om wraak te nemen.\nShane's eerste dienstdag loopt al snel uit op een nachtmerrie.\n\nGEGEVENS:\ncategorie: crime / triller\nkwaliteit: DVDR\ntaal: Engels\nsub: Nederlands ingebakken\nland van herkomst :USA\njaar: 2010\nGrootte: 696 mb\ntijdsduur: 97 min\nbestand: Divx\nvideo codec: XVID\nbitrate: 978 Kbps\nafmetinge: 688 X 384\ngeluidsindeling: lame mp3 128 kbps\n\nINFO: &lt;a href=&quot;\nhttp://www.imdb.com/title/tt1530983/&quot; rel=&quot;nofollow&quot; target=&quot;_NEW&quot;&gt;\nhttp://www.imdb.com/title/tt1530983/&lt;/a&gt; &lt;a href=&quot;\nhttp://www.moviemeter.nl/film/63881&quot; rel=&quot;nofollow&quot; target=&quot;_NEW&quot;&gt;\nhttp://www.moviemeter.nl/film/63881&lt;/a&gt;\n------------------------------------------------------------------------------------------------------------------------------------------------------------------------- &lt;a href=&quot;\nhttp://www.nlt.ons-forum.nl&quot; rel=&quot;nofollow&quot; target=&quot;_NEW&quot;&gt;\nhttp://www.nlt.ons-forum.nl&lt;/a&gt;\nENJOY THE MOVIE :D ","torrent":{"xt":"urn:btih:21d4a981280cf35313a88d6a0feb5ee2fc89186d","amp;dn":"Red+hill+%282010%29+DVDR+NL+Sub+NLT-Release+%28divx%29","amp;tr":["udp%3A%2F%2Ftracker.openbittorrent.com%3A80","udp%3A%2F%2Fopen.demonii.com%3A1337","udp%3A%2F%2Ftracker.coppersurfer.tk%3A6969","udp%3A%2F%2Fexodus.desync.com%3A6969"],"infoHash":"21d4a981280cf35313a88d6a0feb5ee2fc89186d","infoHashBuffer":{"type":"Buffer","data":[33,212,169,129,40,12,243,83,19,168,141,106,15,235,94,226,252,137,24,109]},"announce":[],"urlList":[]}}