{"title":"Your.Highness.2011.UNRATED.720p.BRRiP.XviD.AC3-Rx","uid":6569174,"size":3203528412,"categoryP":"video","categoryS":"hd___movies","magnet":"?xt=urn:btih:31256666d31f7d76608e81f45c4a98fb0ea09713&amp;dn=Your.Highness.2011.UNRATED.720p.BRRiP.XviD.AC3-Rx&amp;tr=udp%3A%2F%2Ftracker.openbittorrent.com%3A80&amp;tr=udp%3A%2F%2Fopen.demonii.com%3A1337&amp;tr=udp%3A%2F%2Ftracker.coppersurfer.tk%3A6969&amp;tr=udp%3A%2F%2Fexodus.desync.com%3A6969","seeders":1,"leechers":1,"uploader":"UltraTorrents","files":3,"time":1311867565,"description":"\nnfo, Poster &amp; Trailer:\n      &lt;a href=&quot;\nhttp://sharepixon.net/movies/your-highness&quot; rel=&quot;nofollow&quot; target=&quot;_NEW&quot;&gt;\nhttp://sharepixon.net/movies/your-highness&lt;/a&gt;\n\n\t\t\t\t\t","torrent":{"xt":"urn:btih:31256666d31f7d76608e81f45c4a98fb0ea09713","amp;dn":"Your.Highness.2011.UNRATED.720p.BRRiP.XviD.AC3-Rx","amp;tr":["udp%3A%2F%2Ftracker.openbittorrent.com%3A80","udp%3A%2F%2Fopen.demonii.com%3A1337","udp%3A%2F%2Ftracker.coppersurfer.tk%3A6969","udp%3A%2F%2Fexodus.desync.com%3A6969"],"infoHash":"31256666d31f7d76608e81f45c4a98fb0ea09713","infoHashBuffer":{"type":"Buffer","data":[49,37,102,102,211,31,125,118,96,142,129,244,92,74,152,251,14,160,151,19]},"announce":[],"urlList":[]}}