{"title":"Quebec.Lesbian.Fetish.XXX.DVDRiP","uid":9246426,"size":911920957,"categoryP":"porn","categoryS":"movies","magnet":"?xt=urn:btih:33f44bf51e2a327b4926f4022a972ab9f805a076&amp;dn=Quebec.Lesbian.Fetish.XXX.DVDRiP&amp;tr=udp%3A%2F%2Ftracker.openbittorrent.com%3A80&amp;tr=udp%3A%2F%2Fopen.demonii.com%3A1337&amp;tr=udp%3A%2F%2Ftracker.coppersurfer.tk%3A6969&amp;tr=udp%3A%2F%2Fexodus.desync.com%3A6969","seeders":1,"leechers":0,"uploader":"xxxlavalxxx","files":3,"time":1385338378,"description":"Category All Girl, Girl-Girl, Foreign\n\nDirector KK\nStarring Kimberly Franklin, Desiree, Yumi, Kream, Anna Nikova, Anny Lee, Erika Heaven, Vandal Vyxen, Livia Monroe\n\nFeaturing: Vandal Vyxen &amp; Kream!\n\nBienvenue au Quebec/Welcome to Quebec. The girls are hotter, spicier and sluttier than the rest of Canada. When Sexy French girls are involved nothing is off limits. It's all lesbian and all dripping with love juice!\n\n &lt;a href=&quot;\nhttp://imgdone.com/viewer.php?file=11616443184844802618.jpg&quot; rel=&quot;nofollow&quot; target=&quot;_NEW&quot;&gt;\nhttp://imgdone.com/viewer.php?file=11616443184844802618.jpg&lt;/a&gt;\n &lt;a href=&quot;\nhttp://imgdone.com/viewer.php?file=84660434108445014724.jpg&quot; rel=&quot;nofollow&quot; target=&quot;_NEW&quot;&gt;\nhttp://imgdone.com/viewer.php?file=84660434108445014724.jpg&lt;/a&gt;","torrent":{"xt":"urn:btih:33f44bf51e2a327b4926f4022a972ab9f805a076","amp;dn":"Quebec.Lesbian.Fetish.XXX.DVDRiP","amp;tr":["udp%3A%2F%2Ftracker.openbittorrent.com%3A80","udp%3A%2F%2Fopen.demonii.com%3A1337","udp%3A%2F%2Ftracker.coppersurfer.tk%3A6969","udp%3A%2F%2Fexodus.desync.com%3A6969"],"infoHash":"33f44bf51e2a327b4926f4022a972ab9f805a076","infoHashBuffer":{"type":"Buffer","data":[51,244,75,245,30,42,50,123,73,38,244,2,42,151,42,185,248,5,160,118]},"announce":[],"urlList":[]}}