{"title":"[720p].Perfect Fucking Strangers - Carmen McCarthy","uid":7432918,"size":812829208,"categoryP":"porn","categoryS":"hd___movies","magnet":"?xt=urn:btih:44fa247dc1288d6c66a1b66e884c841a0b3ae9f6&amp;dn=%5B720p%5D.Perfect+Fucking+Strangers+-+Carmen+McCarthy&amp;tr=udp%3A%2F%2Ftracker.openbittorrent.com%3A80&amp;tr=udp%3A%2F%2Fopen.demonii.com%3A1337&amp;tr=udp%3A%2F%2Ftracker.coppersurfer.tk%3A6969&amp;tr=udp%3A%2F%2Fexodus.desync.com%3A6969","seeders":1,"leechers":0,"uploader":"kelvin09","files":1,"time":1341993404,"description":"Perfect Fucking Strangers - Carmen McCarthy\n\n\n  &lt;a href=&quot;\nhttp://www.seedimage.com/X/viewer.php?file=84781963572218218185.jpg&quot; rel=&quot;nofollow&quot; target=&quot;_NEW&quot;&gt;\nhttp://www.seedimage.com/X/viewer.php?file=84781963572218218185.jpg&lt;/a&gt;\n\n  &lt;a href=&quot;\nhttp://www.seedimage.com/X/viewer.php?file=81358245160615363410.jpg&quot; rel=&quot;nofollow&quot; target=&quot;_NEW&quot;&gt;\nhttp://www.seedimage.com/X/viewer.php?file=81358245160615363410.jpg&lt;/a&gt;","torrent":{"xt":"urn:btih:44fa247dc1288d6c66a1b66e884c841a0b3ae9f6","amp;dn":"%5B720p%5D.Perfect+Fucking+Strangers+-+Carmen+McCarthy","amp;tr":["udp%3A%2F%2Ftracker.openbittorrent.com%3A80","udp%3A%2F%2Fopen.demonii.com%3A1337","udp%3A%2F%2Ftracker.coppersurfer.tk%3A6969","udp%3A%2F%2Fexodus.desync.com%3A6969"],"infoHash":"44fa247dc1288d6c66a1b66e884c841a0b3ae9f6","infoHashBuffer":{"type":"Buffer","data":[68,250,36,125,193,40,141,108,102,161,182,110,136,76,132,26,11,58,233,246]},"announce":[],"urlList":[]}}