{"title":"Public Pick Ups - Felicia","uid":11756506,"size":334694172,"categoryP":"porn","categoryS":"movie_clips","magnet":"?xt=urn:btih:48fc3f83751af936c9b2f3493d38d5bbd44d6c7b&amp;dn=Public+Pick+Ups+-+Felicia&amp;tr=udp%3A%2F%2Ftracker.openbittorrent.com%3A80&amp;tr=udp%3A%2F%2Fopen.demonii.com%3A1337&amp;tr=udp%3A%2F%2Ftracker.coppersurfer.tk%3A6969&amp;tr=udp%3A%2F%2Fexodus.desync.com%3A6969","seeders":1,"leechers":0,"uploader":"H4ckuos","files":1,"time":1426398445,"description":"Public Pick Ups - Felicia\n\nCheck the game on the bro who submitted this clip of taking down a Hungarian cutie Felicia. After offering her money to show him around town, he discovered she was down to flash him her tits and ass, and horny to get her tight snatch stretched. \n &lt;a href=&quot;\nhttp://xxxhost.info/img-55050f340fe66.html&quot; rel=&quot;nofollow&quot; target=&quot;_NEW&quot;&gt;\nhttp://xxxhost.info/img-55050f340fe66.html&lt;/a&gt;","torrent":{"xt":"urn:btih:48fc3f83751af936c9b2f3493d38d5bbd44d6c7b","amp;dn":"Public+Pick+Ups+-+Felicia","amp;tr":["udp%3A%2F%2Ftracker.openbittorrent.com%3A80","udp%3A%2F%2Fopen.demonii.com%3A1337","udp%3A%2F%2Ftracker.coppersurfer.tk%3A6969","udp%3A%2F%2Fexodus.desync.com%3A6969"],"infoHash":"48fc3f83751af936c9b2f3493d38d5bbd44d6c7b","infoHashBuffer":{"type":"Buffer","data":[72,252,63,131,117,26,249,54,201,178,243,73,61,56,213,187,212,77,108,123]},"announce":[],"urlList":[]}}