{"title":"Kogan Page The First-Time Manager - The First Steps To A Brillia","uid":3704540,"size":2535011,"categoryP":"other","categoryS":"e_books","magnet":"?xt=urn:btih:58bfc8cbcc506a373749659c6f67348468b6ade3&amp;dn=Kogan+Page+The+First-Time+Manager+-+The+First+Steps+To+A+Brillia&amp;tr=udp%3A%2F%2Ftracker.openbittorrent.com%3A80&amp;tr=udp%3A%2F%2Fopen.demonii.com%3A1337&amp;tr=udp%3A%2F%2Ftracker.coppersurfer.tk%3A6969&amp;tr=udp%3A%2F%2Fexodus.desync.com%3A6969","seeders":1,"leechers":0,"uploader":"losttheory","files":1,"time":1180881424,"description":"enjoy","torrent":{"xt":"urn:btih:58bfc8cbcc506a373749659c6f67348468b6ade3","amp;dn":"Kogan+Page+The+First-Time+Manager+-+The+First+Steps+To+A+Brillia","amp;tr":["udp%3A%2F%2Ftracker.openbittorrent.com%3A80","udp%3A%2F%2Fopen.demonii.com%3A1337","udp%3A%2F%2Ftracker.coppersurfer.tk%3A6969","udp%3A%2F%2Fexodus.desync.com%3A6969"],"infoHash":"58bfc8cbcc506a373749659c6f67348468b6ade3","infoHashBuffer":{"type":"Buffer","data":[88,191,200,203,204,80,106,55,55,73,101,156,111,103,52,132,104,182,173,227]},"announce":[],"urlList":[]}}