{"title":"Kourtney.and.Khloe.Take.Miami.S02E02.Wax.On.Wax.Off.HDTV.XviD-MO","uid":5647580,"size":182086266,"categoryP":"video","categoryS":"tv_shows","magnet":"?xt=urn:btih:61462d11f7a27f67f97c30aa3a29140bd7c7ec5d&amp;dn=Kourtney.and.Khloe.Take.Miami.S02E02.Wax.On.Wax.Off.HDTV.XviD-MO&amp;tr=udp%3A%2F%2Ftracker.openbittorrent.com%3A80&amp;tr=udp%3A%2F%2Fopen.demonii.com%3A1337&amp;tr=udp%3A%2F%2Ftracker.coppersurfer.tk%3A6969&amp;tr=udp%3A%2F%2Fexodus.desync.com%3A6969","seeders":1,"leechers":0,"uploader":"TvTeam","files":5,"time":1277396825,"description":". \n \n &lt;a href=&quot;\nhttp://www.torrentday.com&quot; rel=&quot;nofollow&quot; target=&quot;_NEW&quot;&gt;\nhttp://www.torrentday.com&lt;/a&gt; :  Your Key To The Scene.\n\n\nNow TvTeam with [No-RAR] Releases.\n\n\n(((((((((((((= Enjoy No RAR releases =))))))))))))))))))))\n\n...................................NFO:....................................\n\n.Kourtney.and.Khloe.Take.Miami.S02E02.Wax.On.Wax.Off.HDTV.XviD-MOMENTUM\n2010-06-24\n\nFilesize.........: 173.6 MB\nRuntime..........: 00:22:08\nVideo ...........: 979 kb/s XviD\nAudio ...........: 108 kb/s, 2ch MP3\nFrame Size.......: 624x352","torrent":{"xt":"urn:btih:61462d11f7a27f67f97c30aa3a29140bd7c7ec5d","amp;dn":"Kourtney.and.Khloe.Take.Miami.S02E02.Wax.On.Wax.Off.HDTV.XviD-MO","amp;tr":["udp%3A%2F%2Ftracker.openbittorrent.com%3A80","udp%3A%2F%2Fopen.demonii.com%3A1337","udp%3A%2F%2Ftracker.coppersurfer.tk%3A6969","udp%3A%2F%2Fexodus.desync.com%3A6969"],"infoHash":"61462d11f7a27f67f97c30aa3a29140bd7c7ec5d","infoHashBuffer":{"type":"Buffer","data":[97,70,45,17,247,162,127,103,249,124,48,170,58,41,20,11,215,199,236,93]},"announce":[],"urlList":[]}}