{"title":"WWE.Monday.Night.RAW.2014.01.27.HDTV.x264-KYR","uid":9540051,"size":1459977638,"categoryP":"video","categoryS":"tv_shows","magnet":"?xt=urn:btih:69643308b706b11bc21cc03baedaf32d05fa6aab&amp;dn=WWE.Monday.Night.RAW.2014.01.27.HDTV.x264-KYR&amp;tr=udp%3A%2F%2Ftracker.openbittorrent.com%3A80&amp;tr=udp%3A%2F%2Fopen.demonii.com%3A1337&amp;tr=udp%3A%2F%2Ftracker.coppersurfer.tk%3A6969&amp;tr=udp%3A%2F%2Fexodus.desync.com%3A6969","seeders":1,"leechers":0,"uploader":"sceneline","files":34,"time":1391022006,"description":"-\n\nFor the sake of sharing, Please seed as long as you can\n\nEnjoy SD releases \n\n ............ NFO .............\n-\t\nFor more info about this show check NFO file\n-","torrent":{"xt":"urn:btih:69643308b706b11bc21cc03baedaf32d05fa6aab","amp;dn":"WWE.Monday.Night.RAW.2014.01.27.HDTV.x264-KYR","amp;tr":["udp%3A%2F%2Ftracker.openbittorrent.com%3A80","udp%3A%2F%2Fopen.demonii.com%3A1337","udp%3A%2F%2Ftracker.coppersurfer.tk%3A6969","udp%3A%2F%2Fexodus.desync.com%3A6969"],"infoHash":"69643308b706b11bc21cc03baedaf32d05fa6aab","infoHashBuffer":{"type":"Buffer","data":[105,100,51,8,183,6,177,27,194,28,192,59,174,218,243,45,5,250,106,171]},"announce":[],"urlList":[]}}