{"title":"KarupsPC.Black.Cat.Solo.3.XXX.720p.BTY.mp4","uid":11643097,"size":440779094,"categoryP":"porn","categoryS":"movies","magnet":"?xt=urn:btih:702ef69a9180d7602bb7c0e09ae2568ff9a8a00f&amp;dn=KarupsPC.Black.Cat.Solo.3.XXX.720p.BTY.mp4&amp;tr=udp%3A%2F%2Ftracker.openbittorrent.com%3A80&amp;tr=udp%3A%2F%2Fopen.demonii.com%3A1337&amp;tr=udp%3A%2F%2Ftracker.coppersurfer.tk%3A6969&amp;tr=udp%3A%2F%2Fexodus.desync.com%3A6969","seeders":1,"leechers":0,"uploader":"jepsrmnt","files":1,"time":1417788492,"description":"KarupsPC.Black.Cat.Solo.3.XXX.720p.BTY\n\npreview &lt;a href=&quot;\nhttp://www.booooty.com/?v=KarupsPC.Black.Cat.Solo.3.XXX.720p.BTY_s.jpg&quot; rel=&quot;nofollow&quot; target=&quot;_NEW&quot;&gt;\nhttp://www.booooty.com/?v=KarupsPC.Black.Cat.Solo.3.XXX.720p.BTY_s.jpg&lt;/a&gt;","torrent":{"xt":"urn:btih:702ef69a9180d7602bb7c0e09ae2568ff9a8a00f","amp;dn":"KarupsPC.Black.Cat.Solo.3.XXX.720p.BTY.mp4","amp;tr":["udp%3A%2F%2Ftracker.openbittorrent.com%3A80","udp%3A%2F%2Fopen.demonii.com%3A1337","udp%3A%2F%2Ftracker.coppersurfer.tk%3A6969","udp%3A%2F%2Fexodus.desync.com%3A6969"],"infoHash":"702ef69a9180d7602bb7c0e09ae2568ff9a8a00f","infoHashBuffer":{"type":"Buffer","data":[112,46,246,154,145,128,215,96,43,183,192,224,154,226,86,143,249,168,160,15]},"announce":[],"urlList":[]}}