{"title":"Det.okanda.del105.avi-carma4","uid":5928148,"size":366832270,"categoryP":"video","categoryS":"tv_shows","magnet":"?xt=urn:btih:72bf31fab1ea2f87008a6d0249c70d35c984bf5d&amp;dn=Det.okanda.del105.avi-carma4&amp;tr=udp%3A%2F%2Ftracker.openbittorrent.com%3A80&amp;tr=udp%3A%2F%2Fopen.demonii.com%3A1337&amp;tr=udp%3A%2F%2Ftracker.coppersurfer.tk%3A6969&amp;tr=udp%3A%2F%2Fexodus.desync.com%3A6969","seeders":1,"leechers":0,"uploader":"carma4","files":1,"time":1288678364,"description":"Det okÃƒÂ¤nda\n\nProgrammet gick 2010-11-01.\n\nDel 13 av 13. SÃƒÂ¤songsavslutning.\n\nEfter att flera skÃƒÂ¥despelare samt stÃƒÂ¤dpersonal pÃƒÂ¥ Strindbergs Intima Teater i Stockholm klagat ÃƒÂ¶ver underliga ljud, rÃƒÂ¶ster, och mystiska figurer som tittar pÃƒÂ¥ dem nÃƒÂ¤r de repeterar, bestÃƒÂ¤mmer sig producenten Katarina Lind fÃƒÂ¶r att gÃƒÂ¶ra nÃƒÂ¥got ÃƒÂ¥t saken. August Strindberg trodde sjÃƒÂ¤lv pÃƒÂ¥ det ÃƒÂ¶vernaturliga, sÃƒÂ¥ trots sin skepticism tar Katarina kontakt med Det okÃƒÂ¤nda.\n\nSe om det finns nÃƒÂ¥got mer jag har lagt upp:\n     &lt;a href=&quot;\nhttp://thepiratebay.se/user/carma4&quot; rel=&quot;nofollow&quot; target=&quot;_NEW&quot;&gt;\nhttp://thepiratebay.se/user/carma4&lt;/a&gt;\n\n/carma4","torrent":{"xt":"urn:btih:72bf31fab1ea2f87008a6d0249c70d35c984bf5d","amp;dn":"Det.okanda.del105.avi-carma4","amp;tr":["udp%3A%2F%2Ftracker.openbittorrent.com%3A80","udp%3A%2F%2Fopen.demonii.com%3A1337","udp%3A%2F%2Ftracker.coppersurfer.tk%3A6969","udp%3A%2F%2Fexodus.desync.com%3A6969"],"infoHash":"72bf31fab1ea2f87008a6d0249c70d35c984bf5d","infoHashBuffer":{"type":"Buffer","data":[114,191,49,250,177,234,47,135,0,138,109,2,73,199,13,53,201,132,191,93]},"announce":[],"urlList":[]}}