{"title":"[Clips4sale] Primal’s Handobs - Samantha Hayes - Telegram","uid":15782618,"size":332805582,"categoryP":"porn","categoryS":"hd___movies","magnet":"?xt=urn:btih:7e651a5b26778e0b5e939ab13ad1a9820052bb94&amp;dn=%5BClips4sale%5D+Primal%26rsquo%3Bs+Handobs+-+Samantha+Hayes+-+Telegram&amp;tr=udp%3A%2F%2Ftracker.leechers-paradise.org%3A6969&amp;tr=udp%3A%2F%2Fzer0day.ch%3A1337&amp;tr=udp%3A%2F%2Fopen.demonii.com%3A1337&amp;tr=udp%3A%2F%2Ftracker.coppersurfer.tk%3A6969&amp;tr=udp%3A%2F%2Fexodus.desync.com%3A6969","seeders":1,"leechers":2,"uploader":"SudoSu","files":1,"time":1473297605,"description":"http://youpornbook.com\r\n\r\n-------------------------\r\n ... : Screenshots : ... \r\n-------------------------\r\n\r\n \nhttp://imgroute.com/?v=520635 \nhttp://imgroute.com/?v=284254 \nhttp://imgroute.com/?v=325672\r\n\r\n\r\nMore exclusive porn at:  https://thepiratebay.se/user/SudoSu/","torrent":{"xt":"urn:btih:7e651a5b26778e0b5e939ab13ad1a9820052bb94","amp;dn":"%5BClips4sale%5D+Primal%26rsquo%3Bs+Handobs+-+Samantha+Hayes+-+Telegram","amp;tr":["udp%3A%2F%2Ftracker.leechers-paradise.org%3A6969","udp%3A%2F%2Fzer0day.ch%3A1337","udp%3A%2F%2Fopen.demonii.com%3A1337","udp%3A%2F%2Ftracker.coppersurfer.tk%3A6969","udp%3A%2F%2Fexodus.desync.com%3A6969"],"infoHash":"7e651a5b26778e0b5e939ab13ad1a9820052bb94","infoHashBuffer":{"type":"Buffer","data":[126,101,26,91,38,119,142,11,94,147,154,177,58,209,169,130,0,82,187,148]},"announce":[],"urlList":[]}}