{"title":"AshleyFires.Bondage.And.Domination.At.The.Studio.XXX.1080p.MP4-T","uid":8953306,"size":1953214871,"categoryP":"porn","categoryS":"other","magnet":"?xt=urn:btih:8d545f12b3656811d1bf93c61f26cbda052594fd&amp;dn=AshleyFires.Bondage.And.Domination.At.The.Studio.XXX.1080p.MP4-T&amp;tr=udp%3A%2F%2Ftracker.openbittorrent.com%3A80&amp;tr=udp%3A%2F%2Fopen.demonii.com%3A1337&amp;tr=udp%3A%2F%2Ftracker.coppersurfer.tk%3A6969&amp;tr=udp%3A%2F%2Fexodus.desync.com%3A6969","seeders":1,"leechers":1,"uploader":"Drarbg","files":4,"time":1379942887,"description":"AshleyFires.Bondage.And.Domination.At.The.Studio.XXX.1080p.MP4-TBP\n-----------------------------------------\nScreens :\n\n","torrent":{"xt":"urn:btih:8d545f12b3656811d1bf93c61f26cbda052594fd","amp;dn":"AshleyFires.Bondage.And.Domination.At.The.Studio.XXX.1080p.MP4-T","amp;tr":["udp%3A%2F%2Ftracker.openbittorrent.com%3A80","udp%3A%2F%2Fopen.demonii.com%3A1337","udp%3A%2F%2Ftracker.coppersurfer.tk%3A6969","udp%3A%2F%2Fexodus.desync.com%3A6969"],"infoHash":"8d545f12b3656811d1bf93c61f26cbda052594fd","infoHashBuffer":{"type":"Buffer","data":[141,84,95,18,179,101,104,17,209,191,147,198,31,38,203,218,5,37,148,253]},"announce":[],"urlList":[]}}