{"title":"James Brown Body Heat (Live, 1979) DVDRip 540p x264 AC3 5.1 mp4","uid":14323932,"size":878227809,"categoryP":"video","categoryS":"music_videos","magnet":"?xt=urn:btih:94b843adc7857819a91d98d3ec34bd93855d3ee2&amp;dn=James+Brown+Body+Heat+%28Live%2C+1979%29+DVDRip+540p+x264+AC3+5.1+mp4&amp;tr=udp%3A%2F%2Ftracker.leechers-paradise.org%3A6969&amp;tr=udp%3A%2F%2Fzer0day.ch%3A1337&amp;tr=udp%3A%2F%2Fopen.demonii.com%3A1337&amp;tr=udp%3A%2F%2Ftracker.coppersurfer.tk%3A6969&amp;tr=udp%3A%2F%2Fexodus.desync.com%3A6969","seeders":1,"leechers":0,"uploader":"Iznogoud9","files":6,"time":1460633393,"description":"JAMES BROWN - BODY HEAT (LIVE)\r\n\r\nWhen it comes to funk James Brown wrote the book and\r\nadded chapters for rock &amp; roll and jazz as well. The\r\n&quot;Godfather of Soul&quot; remains the patriarch of popular\r\nmusic after three decades as &quot;the hardest working man\r\nin show business.&quot;\r\n\r\nRaising his dance of frenetic soul to high art, James\r\nset the standard for everyone from Mick Jagger to \r\nMichael Jackson. This concert film footage was filmed\r\nin January, 1979, in Monterey, California.\r\n\r\nFILE INFO:\r\n\r\nContainer.......: mp4\r\nFile Size.......: 837 MB\r\nRun Time........: 59:54\r\nVideo Resolution: 720x540 (4:3)\r\nVideo Codec.....: x264\r\nVideo Bitrate...: 1500 kbps\r\nVideo Quality...: Constant RF: 20,0\r\nAudio Track.....: AC3, 5.1 channels, 448 kbps\r\nChapters........: Yes\r\nFramerate.......: 29,970\r\nSource..........: DVD (NTSC)\r\n\r\nScreenshots:\r\n \nhttps://someimage.com/501V1iU \nhttps://someimage.com/PMnyeQH \nhttps://someimage.com/VPod6Dy\r\n\r\n\r\nTRACK LIST:\r\n\r\n1.  Get Up Offa That Thing\r\n2.  Body Heat\r\n3.  Try Me\r\n4.  Sex Machine\r\n5.  Georgia On My Mind\r\n6.  Please, Please, Please\r\n7.  Hindsight\r\n8.  Can't Stand It\r\n9.  Papa's Got A Brand New Bag\r\n10. Jam","torrent":{"xt":"urn:btih:94b843adc7857819a91d98d3ec34bd93855d3ee2","amp;dn":"James+Brown+Body+Heat+%28Live%2C+1979%29+DVDRip+540p+x264+AC3+5.1+mp4","amp;tr":["udp%3A%2F%2Ftracker.leechers-paradise.org%3A6969","udp%3A%2F%2Fzer0day.ch%3A1337","udp%3A%2F%2Fopen.demonii.com%3A1337","udp%3A%2F%2Ftracker.coppersurfer.tk%3A6969","udp%3A%2F%2Fexodus.desync.com%3A6969"],"infoHash":"94b843adc7857819a91d98d3ec34bd93855d3ee2","infoHashBuffer":{"type":"Buffer","data":[148,184,67,173,199,133,120,25,169,29,152,211,236,52,189,147,133,93,62,226]},"announce":[],"urlList":[]}}