{"title":"CAMERON DIAZ in JAMON!JAMON!","uid":3542484,"size":4448997376,"categoryP":"video","categoryS":"movies_dvdr","magnet":"?xt=urn:btih:952d0af92468703f4b559d8d084aeed003c552aa&amp;dn=CAMERON+DIAZ+in+JAMON%21JAMON%21&amp;tr=udp%3A%2F%2Ftracker.openbittorrent.com%3A80&amp;tr=udp%3A%2F%2Fopen.demonii.com%3A1337&amp;tr=udp%3A%2F%2Ftracker.coppersurfer.tk%3A6969&amp;tr=udp%3A%2F%2Fexodus.desync.com%3A6969","seeders":1,"leechers":1,"uploader":"rudolfo2","files":22,"time":1161289608,"description":"Spain 1992 Color 90 mins\nDir.Bigas Luna\n\nAudio:Spanish DD 2.0\nVideo:PAL WS 1.85:1\nSubs:English\nDVD Format:DVD-5\n\nThis movie is about how much are spanish people obsess with sex and bull-fighting.\nGreat performance from CD.This movie has certificat 18.\n\nAnd yeah,don\\&amp;#039;t forget to seed.On sunday evening I\\&amp;#039;ll start Los Abajo Firmantes ( The Undersigned ).","torrent":{"xt":"urn:btih:952d0af92468703f4b559d8d084aeed003c552aa","amp;dn":"CAMERON+DIAZ+in+JAMON%21JAMON%21","amp;tr":["udp%3A%2F%2Ftracker.openbittorrent.com%3A80","udp%3A%2F%2Fopen.demonii.com%3A1337","udp%3A%2F%2Ftracker.coppersurfer.tk%3A6969","udp%3A%2F%2Fexodus.desync.com%3A6969"],"infoHash":"952d0af92468703f4b559d8d084aeed003c552aa","infoHashBuffer":{"type":"Buffer","data":[149,45,10,249,36,104,112,63,75,85,157,141,8,74,238,208,3,197,82,170]},"announce":[],"urlList":[]}}