{"title":"The Black Eyed Peas - Just Can't Get Enough(Po.Lpcm.NTSC)2011","uid":6381523,"size":194929165,"categoryP":"video","categoryS":"music_videos","magnet":"?xt=urn:btih:9920531e2d62c2e2daf3a8542c366844e66d1cca&amp;dn=The+Black+Eyed+Peas+-+Just+Can%5C%27t+Get+Enough%28Po.Lpcm.NTSC%292011&amp;tr=udp%3A%2F%2Ftracker.openbittorrent.com%3A80&amp;tr=udp%3A%2F%2Fopen.demonii.com%3A1337&amp;tr=udp%3A%2F%2Ftracker.coppersurfer.tk%3A6969&amp;tr=udp%3A%2F%2Fexodus.desync.com%3A6969","seeders":1,"leechers":0,"uploader":"RageHD","files":3,"time":1305045487,"description":"The Black Eyed Peas - Just Can\\'t Get Enough(Po.Lpcm.NTSC)\n\n\n","torrent":{"xt":"urn:btih:9920531e2d62c2e2daf3a8542c366844e66d1cca","amp;dn":"The+Black+Eyed+Peas+-+Just+Can%5C%27t+Get+Enough%28Po.Lpcm.NTSC%292011","amp;tr":["udp%3A%2F%2Ftracker.openbittorrent.com%3A80","udp%3A%2F%2Fopen.demonii.com%3A1337","udp%3A%2F%2Ftracker.coppersurfer.tk%3A6969","udp%3A%2F%2Fexodus.desync.com%3A6969"],"infoHash":"9920531e2d62c2e2daf3a8542c366844e66d1cca","infoHashBuffer":{"type":"Buffer","data":[153,32,83,30,45,98,194,226,218,243,168,84,44,54,104,68,230,109,28,202]},"announce":[],"urlList":[]}}