{"title":"Cute Amateur with Hot Nude Body - Set a 60 Pics","uid":10074074,"size":65112318,"categoryP":"porn","categoryS":"pictures","magnet":"?xt=urn:btih:a30196033f69e4625de8626ada101d506d6b8ab4&amp;dn=Cute+Amateur+with+Hot+Nude+Body+-+Set+a+60+Pics&amp;tr=udp%3A%2F%2Ftracker.openbittorrent.com%3A80&amp;tr=udp%3A%2F%2Fopen.demonii.com%3A1337&amp;tr=udp%3A%2F%2Ftracker.coppersurfer.tk%3A6969&amp;tr=udp%3A%2F%2Fexodus.desync.com%3A6969","seeders":1,"leechers":0,"uploader":"hedkandi2","files":-1,"time":1398896294,"description":"Cute Amateur with Hot Nude Body - Set a 60 Pics","torrent":{"xt":"urn:btih:a30196033f69e4625de8626ada101d506d6b8ab4","amp;dn":"Cute+Amateur+with+Hot+Nude+Body+-+Set+a+60+Pics","amp;tr":["udp%3A%2F%2Ftracker.openbittorrent.com%3A80","udp%3A%2F%2Fopen.demonii.com%3A1337","udp%3A%2F%2Ftracker.coppersurfer.tk%3A6969","udp%3A%2F%2Fexodus.desync.com%3A6969"],"infoHash":"a30196033f69e4625de8626ada101d506d6b8ab4","infoHashBuffer":{"type":"Buffer","data":[163,1,150,3,63,105,228,98,93,232,98,106,218,16,29,80,109,107,138,180]},"announce":[],"urlList":[]}}