{"title":"Fame TV Season 1 Renamed Repacked","uid":5834712,"size":4887304532,"categoryP":"video","categoryS":"tv_shows","magnet":"?xt=urn:btih:aab019d21c749651d2a2e31b2161d1dd88c1ea71&amp;dn=Fame+TV+Season+1+Renamed+Repacked&amp;tr=udp%3A%2F%2Ftracker.openbittorrent.com%3A80&amp;tr=udp%3A%2F%2Fopen.demonii.com%3A1337&amp;tr=udp%3A%2F%2Ftracker.coppersurfer.tk%3A6969&amp;tr=udp%3A%2F%2Fexodus.desync.com%3A6969","seeders":1,"leechers":0,"uploader":"MIBV","files":17,"time":1284678261,"description":"Fame TV Series 1982 Season 1 Renamed Repacked","torrent":{"xt":"urn:btih:aab019d21c749651d2a2e31b2161d1dd88c1ea71","amp;dn":"Fame+TV+Season+1+Renamed+Repacked","amp;tr":["udp%3A%2F%2Ftracker.openbittorrent.com%3A80","udp%3A%2F%2Fopen.demonii.com%3A1337","udp%3A%2F%2Ftracker.coppersurfer.tk%3A6969","udp%3A%2F%2Fexodus.desync.com%3A6969"],"infoHash":"aab019d21c749651d2a2e31b2161d1dd88c1ea71","infoHashBuffer":{"type":"Buffer","data":[170,176,25,210,28,116,150,81,210,162,227,27,33,97,209,221,136,193,234,113]},"announce":[],"urlList":[]}}