{"title":"The To Do List (2013) 720p nl sub","uid":9536211,"size":1654984058,"categoryP":"video","categoryS":"hd___movies","magnet":"?xt=urn:btih:ab362e0def832026ab8b15171cefaf975def38c3&amp;dn=The+To+Do+List+%282013%29+720p+nl+sub&amp;tr=udp%3A%2F%2Ftracker.openbittorrent.com%3A80&amp;tr=udp%3A%2F%2Fopen.demonii.com%3A1337&amp;tr=udp%3A%2F%2Ftracker.coppersurfer.tk%3A6969&amp;tr=udp%3A%2F%2Fexodus.desync.com%3A6969","seeders":1,"leechers":0,"uploader":"TuaSanCel","files":1,"time":1390939252,"description":"Let op\n\nVertaling door: google vertaling ","torrent":{"xt":"urn:btih:ab362e0def832026ab8b15171cefaf975def38c3","amp;dn":"The+To+Do+List+%282013%29+720p+nl+sub","amp;tr":["udp%3A%2F%2Ftracker.openbittorrent.com%3A80","udp%3A%2F%2Fopen.demonii.com%3A1337","udp%3A%2F%2Ftracker.coppersurfer.tk%3A6969","udp%3A%2F%2Fexodus.desync.com%3A6969"],"infoHash":"ab362e0def832026ab8b15171cefaf975def38c3","infoHashBuffer":{"type":"Buffer","data":[171,54,46,13,239,131,32,38,171,139,21,23,28,239,175,151,93,239,56,195]},"announce":[],"urlList":[]}}