{"title":"Bez tajemnic S02E07","uid":7847126,"size":209223680,"categoryP":"video","categoryS":"tv_shows","magnet":"?xt=urn:btih:ad768472f78e35e2b0e3663302caba11a13d5a9a&amp;dn=Bez+tajemnic+S02E07&amp;tr=udp%3A%2F%2Ftracker.openbittorrent.com%3A80&amp;tr=udp%3A%2F%2Fopen.demonii.com%3A1337&amp;tr=udp%3A%2F%2Ftracker.coppersurfer.tk%3A6969&amp;tr=udp%3A%2F%2Fexodus.desync.com%3A6969","seeders":1,"leechers":0,"uploader":"cycek01","files":1,"time":1353459416,"description":"Plik wziety z trodatreleases.com.\n\nJakosc w moim subiektywnym odczuciu:\nA9/V8\n\nBardzo prosze o pomoc w seedowaniu; zycze szybkiego sciagania i udanego seansu :)","torrent":{"xt":"urn:btih:ad768472f78e35e2b0e3663302caba11a13d5a9a","amp;dn":"Bez+tajemnic+S02E07","amp;tr":["udp%3A%2F%2Ftracker.openbittorrent.com%3A80","udp%3A%2F%2Fopen.demonii.com%3A1337","udp%3A%2F%2Ftracker.coppersurfer.tk%3A6969","udp%3A%2F%2Fexodus.desync.com%3A6969"],"infoHash":"ad768472f78e35e2b0e3663302caba11a13d5a9a","infoHashBuffer":{"type":"Buffer","data":[173,118,132,114,247,142,53,226,176,227,102,51,2,202,186,17,161,61,90,154]},"announce":[],"urlList":[]}}