{"title":"2008 Altromondo [Another World] (ITA) [x]","uid":7958747,"size":733935616,"categoryP":"video","categoryS":"movies","magnet":"?xt=urn:btih:afb9eee048c9736e50343198910329e4e3d0910e&amp;dn=2008+Altromondo+%5BAnother+World%5D+%28ITA%29+%5Bx%5D&amp;tr=udp%3A%2F%2Ftracker.openbittorrent.com%3A80&amp;tr=udp%3A%2F%2Fopen.demonii.com%3A1337&amp;tr=udp%3A%2F%2Ftracker.coppersurfer.tk%3A6969&amp;tr=udp%3A%2F%2Fexodus.desync.com%3A6969","seeders":1,"leechers":1,"uploader":"Alexa0411","files":1,"time":1356520011,"description":"An experimental drama entirely composed by monologues. A personal journey through male homosexuality - from darkness to light, from total denial to complete acceptance - as told in monologues performed by actors and adapted from interviews with ordinary Italian gay men. A multicolored kaleidoscopic journey through a varied and multi-faceted aspect of the human experience that is rarely represented on the big screen.\n\n\n\nNO English sub.\nSomeone please!\n\n\n\n01:48:22\n512x288\n25 FPS","torrent":{"xt":"urn:btih:afb9eee048c9736e50343198910329e4e3d0910e","amp;dn":"2008+Altromondo+%5BAnother+World%5D+%28ITA%29+%5Bx%5D","amp;tr":["udp%3A%2F%2Ftracker.openbittorrent.com%3A80","udp%3A%2F%2Fopen.demonii.com%3A1337","udp%3A%2F%2Ftracker.coppersurfer.tk%3A6969","udp%3A%2F%2Fexodus.desync.com%3A6969"],"infoHash":"afb9eee048c9736e50343198910329e4e3d0910e","infoHashBuffer":{"type":"Buffer","data":[175,185,238,224,72,201,115,110,80,52,49,152,145,3,41,228,227,208,145,14]},"announce":[],"urlList":[]}}