{"title":"American.Dad.S05E05.Man.in.the.Moonbounce.PDTV.XviD-FQM.[VTV].av","uid":5154009,"size":183862284,"categoryP":"video","categoryS":"tv_shows","magnet":"?xt=urn:btih:b0c6eb2ab74c782bb7a2b99502c8afacd3ff48de&amp;dn=American.Dad.S05E05.Man.in.the.Moonbounce.PDTV.XviD-FQM.%5BVTV%5D.av&amp;tr=udp%3A%2F%2Ftracker.openbittorrent.com%3A80&amp;tr=udp%3A%2F%2Fopen.demonii.com%3A1337&amp;tr=udp%3A%2F%2Ftracker.coppersurfer.tk%3A6969&amp;tr=udp%3A%2F%2Fexodus.desync.com%3A6969","seeders":1,"leechers":0,"uploader":"VTV","files":1,"time":1257734160,"description":"American Dad 5x05 (PDTV-FQM)[VTV]","torrent":{"xt":"urn:btih:b0c6eb2ab74c782bb7a2b99502c8afacd3ff48de","amp;dn":"American.Dad.S05E05.Man.in.the.Moonbounce.PDTV.XviD-FQM.%5BVTV%5D.av","amp;tr":["udp%3A%2F%2Ftracker.openbittorrent.com%3A80","udp%3A%2F%2Fopen.demonii.com%3A1337","udp%3A%2F%2Ftracker.coppersurfer.tk%3A6969","udp%3A%2F%2Fexodus.desync.com%3A6969"],"infoHash":"b0c6eb2ab74c782bb7a2b99502c8afacd3ff48de","infoHashBuffer":{"type":"Buffer","data":[176,198,235,42,183,76,120,43,183,162,185,149,2,200,175,172,211,255,72,222]},"announce":[],"urlList":[]}}