{"title":"Twistys.14.06.01.Aidra.Fox.What.A.Fox.XXX.IMAGESET-GAGBALL","uid":10271187,"size":71971326,"categoryP":"porn","categoryS":"other","magnet":"?xt=urn:btih:bf446a9314cc1965f071372459b64347826e77a7&amp;dn=Twistys.14.06.01.Aidra.Fox.What.A.Fox.XXX.IMAGESET-GAGBALL&amp;tr=udp%3A%2F%2Ftracker.openbittorrent.com%3A80&amp;tr=udp%3A%2F%2Fopen.demonii.com%3A1337&amp;tr=udp%3A%2F%2Ftracker.coppersurfer.tk%3A6969&amp;tr=udp%3A%2F%2Fexodus.desync.com%3A6969","seeders":1,"leechers":1,"uploader":"Drarbg","files":101,"time":1401589311,"description":"Twistys.com_14.06.01.Aidra.Fox.What.A.Fox.XXX.IMAGESET-GAGBALL\n","torrent":{"xt":"urn:btih:bf446a9314cc1965f071372459b64347826e77a7","amp;dn":"Twistys.14.06.01.Aidra.Fox.What.A.Fox.XXX.IMAGESET-GAGBALL","amp;tr":["udp%3A%2F%2Ftracker.openbittorrent.com%3A80","udp%3A%2F%2Fopen.demonii.com%3A1337","udp%3A%2F%2Ftracker.coppersurfer.tk%3A6969","udp%3A%2F%2Fexodus.desync.com%3A6969"],"infoHash":"bf446a9314cc1965f071372459b64347826e77a7","infoHashBuffer":{"type":"Buffer","data":[191,68,106,147,20,204,25,101,240,113,55,36,89,182,67,71,130,110,119,167]},"announce":[],"urlList":[]}}