{"title":"The.Daily.Show.2012.11.27.Warren.Buffett.720p.HDTV.x264-LMAO","uid":7866589,"size":434469949,"categoryP":"video","categoryS":"hd___tv_shows","magnet":"?xt=urn:btih:cf76c2fd916bf07462d772c047c14ae7ceb75a6f&amp;dn=The.Daily.Show.2012.11.27.Warren.Buffett.720p.HDTV.x264-LMAO&amp;tr=udp%3A%2F%2Ftracker.openbittorrent.com%3A80&amp;tr=udp%3A%2F%2Fopen.demonii.com%3A1337&amp;tr=udp%3A%2F%2Ftracker.coppersurfer.tk%3A6969&amp;tr=udp%3A%2F%2Fexodus.desync.com%3A6969","seeders":1,"leechers":3,"uploader":"sceneline","files":13,"time":1354082472,"description":"- &lt;a href=&quot;\nhttp://www.Speed.Cd&quot; rel=&quot;nofollow&quot; target=&quot;_NEW&quot;&gt;\nhttp://www.Speed.Cd&lt;/a&gt;\n &lt;a href=&quot;\nhttp://www.Speed.Cd&quot; rel=&quot;nofollow&quot; target=&quot;_NEW&quot;&gt;\nhttp://www.Speed.Cd&lt;/a&gt;       the fast  and The Hottest Private Tracker on the net\n\nPlease Seed back to make the speed Faster!!\n ............ NFO .............\n-         \n                ()    _______    ____  ____   ______     ______\n   #           #|  |       |  |    /    |/         /        \n   #      _    #   | |       |  |          |          |          |\n   # _   ~()~  #  /  |       |__|          |          |     _    |\n   #| |  /))   #_|   |          |          |    /    |    | |   |\n   #| |_/ |    #     |          |          |   |__|   |    |_|   |\n   #`.   )    #     |          |          |    __    |          |\n   #  )_( /_   #     |__________|___|/|___|___|  |___|________/\n __________________________________________________________________\n|__________________________________________________________________|\n \n   //-&gt; Info:\n\n The.Daily.Show.2012.11.27.Warren.Buffett.720p.HDTV.x264-LMAO                \n                                     \n      Release Date...: 2012-11-28                                   \n      Release Size...: 414.34Mb                                     \n      Play Time......: 21:28                                        \n      Resolution.....: 1276x720                                     \n      Video Bitrate..: 2311kbps                                     \n      Video Framerate: 29.970                                                \n\n   //-&gt; Notes:\n      \n                                                                   \n                                                                  \n       \n   //-&gt; Greets:\n\n      Your girlfriend, sister, wife, and mom..\n\n __________________________________________________________________\n|__________________________________________________________________|","torrent":{"xt":"urn:btih:cf76c2fd916bf07462d772c047c14ae7ceb75a6f","amp;dn":"The.Daily.Show.2012.11.27.Warren.Buffett.720p.HDTV.x264-LMAO","amp;tr":["udp%3A%2F%2Ftracker.openbittorrent.com%3A80","udp%3A%2F%2Fopen.demonii.com%3A1337","udp%3A%2F%2Ftracker.coppersurfer.tk%3A6969","udp%3A%2F%2Fexodus.desync.com%3A6969"],"infoHash":"cf76c2fd916bf07462d772c047c14ae7ceb75a6f","infoHashBuffer":{"type":"Buffer","data":[207,118,194,253,145,107,240,116,98,215,114,192,71,193,74,231,206,183,90,111]},"announce":[],"urlList":[]}}