{"title":"After Porn Ends DOCU WEBRip X264 AAC-REsuRRecTion","uid":8420827,"size":1370747114,"categoryP":"video","categoryS":"movies","magnet":"?xt=urn:btih:e4a25c198ac22aa5eb9b15daafa96cafd3169b96&amp;dn=After+Porn+Ends+DOCU+WEBRip+X264+AAC-REsuRRecTion&amp;tr=udp%3A%2F%2Ftracker.openbittorrent.com%3A80&amp;tr=udp%3A%2F%2Fopen.demonii.com%3A1337&amp;tr=udp%3A%2F%2Ftracker.coppersurfer.tk%3A6969&amp;tr=udp%3A%2F%2Fexodus.desync.com%3A6969","seeders":1,"leechers":0,"uploader":"R0thschild","files":2,"time":1367186231,"description":"--------------------------------------------\n\nAfter Porn Ends (2010)\n  \nReviews: 6 user | 6 critic\nAfter Porn Ends, is a documentary that not only examines the lives and careers of some of the biggest names in the history of the adult entertainment industry; but what happens to them\n\nFileSize/String                  : 1.28 GiB\nDuration/String                  : 1h 30mn\nOverallBitRate/String            : 2019 Kbps\nEncoded_Application              : HandBrake 0.9.8\nEncoded_Library/String           : libmkv 0.6.5\n\nVideo\nID/String                        : 1\nFormat                           : AVC\nFormat/Info                      : Advanced Video Codec\nFormat_Profile                   : &lt;a class=&quot;__cf_email__&quot; href=&quot;/cdn-cgi/l/email-protection&quot; data-cfemail=&quot;0c416d65624c403f223d&quot;&gt;[email&amp;#160;protected]&lt;/a&gt;&lt;script data-cfhash='f9e31' type=&quot;text/javascript&quot;&gt;\n/* &lt;![CDATA[ */!function(){try{var t=&quot;currentScript&quot;in document?document.currentScript:function(){for(var t=document.getElementsByTagName(&quot;script&quot;),e=t.length;e--;)if(t[e].getAttribute(&quot;data-cfhash&quot;))return t[e]}();if(t&amp;&amp;t.previousSibling){var e,r,n,i,c=t.previousSibling,a=c.getAttribute(&quot;data-cfemail&quot;);if(a){for(e=&quot;&quot;,r=parseInt(a.substr(0,2),16),n=2;a.length-n;n+=2)i=parseInt(a.substr(n,2),16)^r,e+=String.fromCharCode(i);e=document.createTextNode(e),c.parentNode.replaceChild(e,c)}t.parentNode.removeChild(t);}}catch(u){}}()/* ]]&gt; */&lt;/script&gt;\nFormat_Settings_CABAC/String     : Yes\nFormat_Settings_RefFrames/String : 4 frame2\nCodecID                          : V_MPEG4/ISO/AVC\nDuration/String                  : 1h 30mn\nWidth/String                     : 1096 pixel3\nHeight/String                    : 614 pixel3\nDisplayAspectRatio/String        : 16:9\nFrameRate_Mode/String            : VFR\nFrameRate/String                 : 25.000 fps3\nColorSpace                       : YUV\nChromaSubsampling                : 4:2:0\nBitDepth/String                  : 8 bit3\nScanType/String                  : Progressive\nEncoded_Library/String           : x264 core 120\n\n\nAudio\nID/String                        : 2\nFormat                           : AAC\nFormat/Info                      : Advanced Audio Codec\nFormat_Version                   : Version 4\nFormat_Profile                   : LC\nCodecID                          : A_AAC\nDuration/String                  : 1h 30mn\nChannel(s)/String                : 2 channel2\nChannelPositions                 : Front: L R\nSamplingRate/String              : 44.1 KHz\n\n--------------------------------------------\n\nMore at   &lt;a href=&quot;\nhttp://publichash.com/&quot; rel=&quot;nofollow&quot; target=&quot;_NEW&quot;&gt;\nhttp://publichash.com/&lt;/a&gt;\n\n--------------------------------------------","torrent":{"xt":"urn:btih:e4a25c198ac22aa5eb9b15daafa96cafd3169b96","amp;dn":"After+Porn+Ends+DOCU+WEBRip+X264+AAC-REsuRRecTion","amp;tr":["udp%3A%2F%2Ftracker.openbittorrent.com%3A80","udp%3A%2F%2Fopen.demonii.com%3A1337","udp%3A%2F%2Ftracker.coppersurfer.tk%3A6969","udp%3A%2F%2Fexodus.desync.com%3A6969"],"infoHash":"e4a25c198ac22aa5eb9b15daafa96cafd3169b96","infoHashBuffer":{"type":"Buffer","data":[228,162,92,25,138,194,42,165,235,155,21,218,175,169,108,175,211,22,155,150]},"announce":[],"urlList":[]}}