{"title":"NITR-064 Reiko Kobayakawa JAV CENSORED","uid":10343898,"size":1542348846,"categoryP":"porn","categoryS":"movie_clips","magnet":"?xt=urn:btih:eaaa5d894815db95c4813ac97b7dcdc51178a343&amp;dn=NITR-064+Reiko+Kobayakawa+JAV+CENSORED&amp;tr=udp%3A%2F%2Ftracker.openbittorrent.com%3A80&amp;tr=udp%3A%2F%2Fopen.demonii.com%3A1337&amp;tr=udp%3A%2F%2Ftracker.coppersurfer.tk%3A6969&amp;tr=udp%3A%2F%2Fexodus.desync.com%3A6969","seeders":1,"leechers":2,"uploader":"3xplanet","files":1,"time":1402534767,"description":"NITR-064 Reiko Kobayakawa JAV CENSORED\nCover &lt;a href=&quot;\nhttp://www.3xplanet.com/view/44563.html&quot; rel=&quot;nofollow&quot; target=&quot;_NEW&quot;&gt;\nhttp://www.3xplanet.com/view/44563.html&lt;/a&gt;\nScreenshot &lt;a href=&quot;\nhttp://www.3xplanet.com/view/44611.html&quot; rel=&quot;nofollow&quot; target=&quot;_NEW&quot;&gt;\nhttp://www.3xplanet.com/view/44611.html&lt;/a&gt;\nTitle: \nStarring: Reiko Kobayakawa\nStudio:  Crystal Video\n\nTag: JAV, CENSORED, Crystal Video, Work alone, panchira, housewife, cum inside, Creampie, Big tits\n\n","torrent":{"xt":"urn:btih:eaaa5d894815db95c4813ac97b7dcdc51178a343","amp;dn":"NITR-064+Reiko+Kobayakawa+JAV+CENSORED","amp;tr":["udp%3A%2F%2Ftracker.openbittorrent.com%3A80","udp%3A%2F%2Fopen.demonii.com%3A1337","udp%3A%2F%2Ftracker.coppersurfer.tk%3A6969","udp%3A%2F%2Fexodus.desync.com%3A6969"],"infoHash":"eaaa5d894815db95c4813ac97b7dcdc51178a343","infoHashBuffer":{"type":"Buffer","data":[234,170,93,137,72,21,219,149,196,129,58,201,123,125,205,197,17,120,163,67]},"announce":[],"urlList":[]}}