{"title":"KarupsPC.16.08.18.Cameron.Defusi.And.Hana.Black.Lesbian.XXX.7...","uid":15595992,"size":756944753,"categoryP":"porn","categoryS":"other","magnet":"?xt=urn:btih:ec8b19bfd26610c98d6d74669c4ea60d612ecc74&amp;dn=KarupsPC.16.08.18.Cameron.Defusi.And.Hana.Black.Lesbian.XXX.7...&amp;tr=udp%3A%2F%2Ftracker.leechers-paradise.org%3A6969&amp;tr=udp%3A%2F%2Fzer0day.ch%3A1337&amp;tr=udp%3A%2F%2Fopen.demonii.com%3A1337&amp;tr=udp%3A%2F%2Ftracker.coppersurfer.tk%3A6969&amp;tr=udp%3A%2F%2Fexodus.desync.com%3A6969","seeders":1,"leechers":2,"uploader":"juggs99","files":3,"time":1471567204,"description":"\nKarupsPC.16.08.18.Cameron.Defusi.And.Hana.Black.Lesbian.XXX.720p.MP4-KTR \r\n\n\n[Format]:    MPEG-4\n[Duration]:    19mn 53s\n[Resolution]:  1 280 x 720 pixels\n[Display aspect ratio]:    16:9\n[Frame rate mode]:    Constant\n[Frame rate]:    23.976 fps\n\r\n\n#N1C -&gt; To avoid fakes, ALWAYS check that the torrent was added by NO1CARES\r \nhttp://extratorrent.cc/\r\n\n\nHelp us by donating with Bitcoin: 1XeH1kKXWYbzZcFHokGiZ4d3MWW5WyXzU\r\n\nScreens...\r \nhttp://www.xxximagetpb.org/image/o8IOc\r \nhttp://www.xxximagetpb.org/image/o8Y2Z\r \nhttp://www.xxximagetpb.org/image/o8mkl\r \nhttp://www.xxximagetpb.org/image/o8FEJ","torrent":{"xt":"urn:btih:ec8b19bfd26610c98d6d74669c4ea60d612ecc74","amp;dn":"KarupsPC.16.08.18.Cameron.Defusi.And.Hana.Black.Lesbian.XXX.7...","amp;tr":["udp%3A%2F%2Ftracker.leechers-paradise.org%3A6969","udp%3A%2F%2Fzer0day.ch%3A1337","udp%3A%2F%2Fopen.demonii.com%3A1337","udp%3A%2F%2Ftracker.coppersurfer.tk%3A6969","udp%3A%2F%2Fexodus.desync.com%3A6969"],"infoHash":"ec8b19bfd26610c98d6d74669c4ea60d612ecc74","infoHashBuffer":{"type":"Buffer","data":[236,139,25,191,210,102,16,201,141,109,116,102,156,78,166,13,97,46,204,116]},"announce":[],"urlList":[]}}